<?xml version="1.0" encoding="UTF-8"?>
<!DOCTYPE mapper PUBLIC "-//mybatis.org//DTD Mapper 3.0//EN" "http://mybatis.org/dtd/mybatis-3-mapper.dtd">
<mapper namespace="com.ums.mbr.service.core.mapper.OrderInfMapper">
  <resultMap id="BaseResultMap" type="com.ums.mbr.service.domain.OrderInf">
    <!--
      WARNING - @mbg.generated
      This element is automatically generated by MyBatis Generator, do not modify.
    -->
    <id column="RETSERIAL" jdbcType="VARCHAR" property="retserial" />
    <result column="ORDER_NO" jdbcType="VARCHAR" property="orderNo" />
    <result column="MCHTNO" jdbcType="VARCHAR" property="mchtno" />
    <result column="TERMNO" jdbcType="VARCHAR" property="termno" />
    <result column="STATE" jdbcType="VARCHAR" property="state" />
    <result column="NOTE" jdbcType="VARCHAR" property="note" />
    <result column="CREATE_TIME" jdbcType="VARCHAR" property="createTime" />
    <result column="REFRESH_TIME" jdbcType="VARCHAR" property="refreshTime" />
    <result column="EFFECTIVE_TIME" jdbcType="VARCHAR" property="effectiveTime" />
  </resultMap>
  <sql id="Example_Where_Clause">
    <!--
      WARNING - @mbg.generated
      This element is automatically generated by MyBatis Generator, do not modify.
    -->
    <where>
      <foreach collection="oredCriteria" item="criteria" separator="or">
        <if test="criteria.valid">
          <trim prefix="(" prefixOverrides="and" suffix=")">
            <foreach collection="criteria.criteria" item="criterion">
              <choose>
                <when test="criterion.noValue">
                  and ${criterion.condition}
                </when>
                <when test="criterion.singleValue">
                  and ${criterion.condition} #{criterion.value}
                </when>
                <when test="criterion.betweenValue">
                  and ${criterion.condition} #{criterion.value} and #{criterion.secondValue}
                </when>
                <when test="criterion.listValue">
                  and ${criterion.condition}
                  <foreach close=")" collection="criterion.value" item="listItem" open="(" separator=",">
                    #{listItem}
                  </foreach>
                </when>
              </choose>
            </foreach>
          </trim>
        </if>
      </foreach>
    </where>
  </sql>
  <sql id="Update_By_Example_Where_Clause">
    <!--
      WARNING - @mbg.generated
      This element is automatically generated by MyBatis Generator, do not modify.
    -->
    <where>
      <foreach collection="example.oredCriteria" item="criteria" separator="or">
        <if test="criteria.valid">
          <trim prefix="(" prefixOverrides="and" suffix=")">
            <foreach collection="criteria.criteria" item="criterion">
              <choose>
                <when test="criterion.noValue">
                  and ${criterion.condition}
                </when>
                <when test="criterion.singleValue">
                  and ${criterion.condition} #{criterion.value}
                </when>
                <when test="criterion.betweenValue">
                  and ${criterion.condition} #{criterion.value} and #{criterion.secondValue}
                </when>
                <when test="criterion.listValue">
                  and ${criterion.condition}
                  <foreach close=")" collection="criterion.value" item="listItem" open="(" separator=",">
                    #{listItem}
                  </foreach>
                </when>
              </choose>
            </foreach>
          </trim>
        </if>
      </foreach>
    </where>
  </sql>
  <sql id="Base_Column_List">
    <!--
      WARNING - @mbg.generated
      This element is automatically generated by MyBatis Generator, do not modify.
    -->
    RETSERIAL, ORDER_NO, MCHTNO, TERMNO, STATE, NOTE, CREATE_TIME, REFRESH_TIME, EFFECTIVE_TIME
  </sql>
  <select id="selectByExample" parameterType="com.ums.mbr.service.core.example.OrderInfExample" resultMap="BaseResultMap">
    <!--
      WARNING - @mbg.generated
      This element is automatically generated by MyBatis Generator, do not modify.
    -->
    select
    <if test="distinct">
      distinct
    </if>
    <include refid="Base_Column_List" />
    from t_orderinf
    <if test="_parameter != null">
      <include refid="Example_Where_Clause" />
    </if>
    <if test="orderByClause != null">
      order by ${orderByClause}
    </if>
  </select>
  <select id="selectByPrimaryKey" parameterType="java.lang.String" resultMap="BaseResultMap">
    <!--
      WARNING - @mbg.generated
      This element is automatically generated by MyBatis Generator, do not modify.
    -->
    select
    <include refid="Base_Column_List" />
    from t_orderinf
    where RETSERIAL = #{retserial,jdbcType=VARCHAR}
  </select>
  <delete id="deleteByPrimaryKey" parameterType="java.lang.String">
    <!--
      WARNING - @mbg.generated
      This element is automatically generated by MyBatis Generator, do not modify.
    -->
    delete from t_orderinf
    where RETSERIAL = #{retserial,jdbcType=VARCHAR}
  </delete>
  <delete id="deleteByExample" parameterType="com.ums.mbr.service.core.example.OrderInfExample">
    <!--
      WARNING - @mbg.generated
      This element is automatically generated by MyBatis Generator, do not modify.
    -->
    delete from t_orderinf
    <if test="_parameter != null">
      <include refid="Example_Where_Clause" />
    </if>
  </delete>
  <insert id="insert" parameterType="com.ums.mbr.service.domain.OrderInf">
    <!--
      WARNING - @mbg.generated
      This element is automatically generated by MyBatis Generator, do not modify.
    -->
    insert into t_orderinf (RETSERIAL, ORDER_NO, MCHTNO,
    TERMNO, STATE, NOTE,
    CREATE_TIME, REFRESH_TIME, EFFECTIVE_TIME
    )
    values (#{retserial,jdbcType=VARCHAR}, #{orderNo,jdbcType=VARCHAR}, #{mchtno,jdbcType=VARCHAR},
    #{termno,jdbcType=VARCHAR}, #{state,jdbcType=VARCHAR}, #{note,jdbcType=VARCHAR},
    #{createTime,jdbcType=VARCHAR}, #{refreshTime,jdbcType=VARCHAR}, #{effectiveTime,jdbcType=VARCHAR}
    )
  </insert>
  <insert id="insertSelective" parameterType="com.ums.mbr.service.domain.OrderInf">
    <!--
      WARNING - @mbg.generated
      This element is automatically generated by MyBatis Generator, do not modify.
    -->
    insert into t_orderinf
    <trim prefix="(" suffix=")" suffixOverrides=",">
      <if test="retserial != null">
        RETSERIAL,
      </if>
      <if test="orderNo != null">
        ORDER_NO,
      </if>
      <if test="mchtno != null">
        MCHTNO,
      </if>
      <if test="termno != null">
        TERMNO,
      </if>
      <if test="state != null">
        STATE,
      </if>
      <if test="note != null">
        NOTE,
      </if>
      <if test="createTime != null">
        CREATE_TIME,
      </if>
      <if test="refreshTime != null">
        REFRESH_TIME,
      </if>
      <if test="effectiveTime != null">
        EFFECTIVE_TIME,
      </if>
    </trim>
    <trim prefix="values (" suffix=")" suffixOverrides=",">
      <if test="retserial != null">
        #{retserial,jdbcType=VARCHAR},
      </if>
      <if test="orderNo != null">
        #{orderNo,jdbcType=VARCHAR},
      </if>
      <if test="mchtno != null">
        #{mchtno,jdbcType=VARCHAR},
      </if>
      <if test="termno != null">
        #{termno,jdbcType=VARCHAR},
      </if>
      <if test="state != null">
        #{state,jdbcType=VARCHAR},
      </if>
      <if test="note != null">
        #{note,jdbcType=VARCHAR},
      </if>
      <if test="createTime != null">
        #{createTime,jdbcType=VARCHAR},
      </if>
      <if test="refreshTime != null">
        #{refreshTime,jdbcType=VARCHAR},
      </if>
      <if test="effectiveTime != null">
        #{effectiveTime,jdbcType=VARCHAR},
      </if>
    </trim>
  </insert>
  <select id="countByExample" parameterType="com.ums.mbr.service.core.example.OrderInfExample" resultType="java.lang.Long">
    <!--
      WARNING - @mbg.generated
      This element is automatically generated by MyBatis Generator, do not modify.
    -->
    select count(*) from t_orderinf
    <if test="_parameter != null">
      <include refid="Example_Where_Clause" />
    </if>
  </select>
  <update id="updateByExampleSelective" parameterType="map">
    <!--
      WARNING - @mbg.generated
      This element is automatically generated by MyBatis Generator, do not modify.
    -->
    update t_orderinf
    <set>
      <if test="record.retserial != null">
        RETSERIAL = #{record.retserial,jdbcType=VARCHAR},
      </if>
      <if test="record.orderNo != null">
        ORDER_NO = #{record.orderNo,jdbcType=VARCHAR},
      </if>
      <if test="record.mchtno != null">
        MCHTNO = #{record.mchtno,jdbcType=VARCHAR},
      </if>
      <if test="record.termno != null">
        TERMNO = #{record.termno,jdbcType=VARCHAR},
      </if>
      <if test="record.state != null">
        STATE = #{record.state,jdbcType=VARCHAR},
      </if>
      <if test="record.note != null">
        NOTE = #{record.note,jdbcType=VARCHAR},
      </if>
      <if test="record.createTime != null">
        CREATE_TIME = #{record.createTime,jdbcType=VARCHAR},
      </if>
      <if test="record.refreshTime != null">
        REFRESH_TIME = #{record.refreshTime,jdbcType=VARCHAR},
      </if>
      <if test="record.effectiveTime != null">
        EFFECTIVE_TIME = #{record.effectiveTime,jdbcType=VARCHAR},
      </if>
    </set>
    <if test="_parameter != null">
      <include refid="Update_By_Example_Where_Clause" />
    </if>
  </update>
  <update id="updateByExample" parameterType="map">
    <!--
      WARNING - @mbg.generated
      This element is automatically generated by MyBatis Generator, do not modify.
    -->
    update t_orderinf
    set RETSERIAL = #{record.retserial,jdbcType=VARCHAR},
    ORDER_NO = #{record.orderNo,jdbcType=VARCHAR},
    MCHTNO = #{record.mchtno,jdbcType=VARCHAR},
    TERMNO = #{record.termno,jdbcType=VARCHAR},
    STATE = #{record.state,jdbcType=VARCHAR},
    NOTE = #{record.note,jdbcType=VARCHAR},
    CREATE_TIME = #{record.createTime,jdbcType=VARCHAR},
    REFRESH_TIME = #{record.refreshTime,jdbcType=VARCHAR},
    EFFECTIVE_TIME = #{record.effectiveTime,jdbcType=VARCHAR}
    <if test="_parameter != null">
      <include refid="Update_By_Example_Where_Clause" />
    </if>
  </update>
  <update id="updateByPrimaryKeySelective" parameterType="com.ums.mbr.service.domain.OrderInf">
    <!--
      WARNING - @mbg.generated
      This element is automatically generated by MyBatis Generator, do not modify.
    -->
    update t_orderinf
    <set>
      <if test="orderNo != null">
        ORDER_NO = #{orderNo,jdbcType=VARCHAR},
      </if>
      <if test="mchtno != null">
        MCHTNO = #{mchtno,jdbcType=VARCHAR},
      </if>
      <if test="termno != null">
        TERMNO = #{termno,jdbcType=VARCHAR},
      </if>
      <if test="state != null">
        STATE = #{state,jdbcType=VARCHAR},
      </if>
      <if test="note != null">
        NOTE = #{note,jdbcType=VARCHAR},
      </if>
      <if test="createTime != null">
        CREATE_TIME = #{createTime,jdbcType=VARCHAR},
      </if>
      <if test="refreshTime != null">
        REFRESH_TIME = #{refreshTime,jdbcType=VARCHAR},
      </if>
      <if test="effectiveTime != null">
        EFFECTIVE_TIME = #{effectiveTime,jdbcType=VARCHAR},
      </if>
    </set>
    where RETSERIAL = #{retserial,jdbcType=VARCHAR}
  </update>
  <update id="updateByOrderNoSelective" parameterType="com.ums.mbr.service.domain.OrderInf">
    <!--
      WARNING - @mbg.generated
      This element is automatically generated by MyBatis Generator, do not modify.
    -->
    update t_orderinf
    <set>
      <if test="mchtno != null">
        MCHTNO = #{mchtno,jdbcType=VARCHAR},
      </if>
      <if test="termno != null">
        TERMNO = #{termno,jdbcType=VARCHAR},
      </if>
      <if test="state != null">
        STATE = #{state,jdbcType=VARCHAR},
      </if>
      <if test="note != null">
        NOTE = #{note,jdbcType=VARCHAR},
      </if>
      <if test="createTime != null">
        CREATE_TIME = #{createTime,jdbcType=VARCHAR},
      </if>
      <if test="refreshTime != null">
        REFRESH_TIME = #{refreshTime,jdbcType=VARCHAR},
      </if>
      <if test="effectiveTime != null">
        EFFECTIVE_TIME = #{effectiveTime,jdbcType=VARCHAR},
      </if>
    </set>
    where ORDER_NO = #{orderNo,jdbcType=VARCHAR}
  </update>
  <update id="updateByPrimaryKey" parameterType="com.ums.mbr.service.domain.OrderInf">
    <!--
      WARNING - @mbg.generated
      This element is automatically generated by MyBatis Generator, do not modify.
    -->
    update t_orderinf
    set ORDER_NO = #{orderNo,jdbcType=VARCHAR},
    MCHTNO = #{mchtno,jdbcType=VARCHAR},
    TERMNO = #{termno,jdbcType=VARCHAR},
    STATE = #{state,jdbcType=VARCHAR},
    NOTE = #{note,jdbcType=VARCHAR},
    CREATE_TIME = #{createTime,jdbcType=VARCHAR},
    REFRESH_TIME = #{refreshTime,jdbcType=VARCHAR},
    EFFECTIVE_TIME = #{effectiveTime,jdbcType=VARCHAR}
    where RETSERIAL = #{retserial,jdbcType=VARCHAR}
  </update>
</mapper>